rubbrband/__init__.py
rubbrband/main.py
rubbrband-0.2.19.dist-info/LICENSE
rubbrband-0.2.19.dist-info/METADATA
rubbrband-0.2.19.dist-info/WHEEL
rubbrband-0.2.19.dist-info/top_level.txt
rubbrband-0.2.19.dist-info/RECORD
