Metadata-Version: 2.1
Name: rubbrband
Version: 0.2.19
Home-page: https://github.com/rubbrband/rubbrband
License-File: LICENSE
Requires-Dist: requests
Requires-Dist: Pillow
